exemakerx/__init__.py
exemakerx/__main__.py
exemakerx-1.0.0.dist-info/METADATA
exemakerx-1.0.0.dist-info/WHEEL
exemakerx-1.0.0.dist-info/entry_points.txt
exemakerx-1.0.0.dist-info/top_level.txt
exemakerx-1.0.0.dist-info/RECORD
