Metadata-Version: 2.4
Name: exemakerx
Version: 1.0.0
Summary: Convert .py files to .exe with GUI and CLI
Home-page: https://github.com/ruzgar/exemakerx
Author: Ruzgar
Classifier: Programming Language :: Python :: 3
Classifier: Operating System :: OS Independent
Requires-Python: >=3.7
Requires-Dist: pyinstaller
Dynamic: author
Dynamic: classifier
Dynamic: description
Dynamic: description-content-type
Dynamic: home-page
Dynamic: requires-dist
Dynamic: requires-python
Dynamic: summary
